setup.py
gitant/__init__.py
gitant.egg-info/PKG-INFO
gitant.egg-info/SOURCES.txt
gitant.egg-info/dependency_links.txt
gitant.egg-info/top_level.txt